<?xml version="1.0" encoding="utf-8"?>
<contentitemdata.k13store.cartsummary>
  <CartNextStep>
    <![CDATA[[{"WebPageGuid":"cb75cf8f-5adb-4fd9-9c02-ec15c43a5fef"}]]]>
  </CartNextStep>
  <CartPreviousStep>
    <![CDATA[[{"WebPageGuid":"77d789b9-9881-48de-9f82-f68ddcd57fbc"}]]]>
  </CartPreviousStep>
  <ContentItemDataCommonDataID>
    <GUID>a2ff1107-ab4c-4e3d-b5e6-a46cf9d7e35d</GUID>
    <ObjectType>cms.contentitemcommondata</ObjectType>
    <Parent>
      <CodeName>CartSummary-2o62tqza</CodeName>
      <GUID>fc2ea89f-160a-4dfe-8aac-e9e3fe45077e</GUID>
      <ObjectType>cms.contentitem</ObjectType>
    </Parent>
  </ContentItemDataCommonDataID>
  <ContentItemDataGUID>82eed25b-1f73-48a2-b6fe-c0a8f3be807b</ContentItemDataGUID>
</contentitemdata.k13store.cartsummary>